earthaccess/__init__.py
earthaccess/api.py
earthaccess/auth.py
earthaccess/daac.py
earthaccess/dmrpp_zarr.py
earthaccess/exceptions.py
earthaccess/formatters.py
earthaccess/kerchunk.py
earthaccess/py.typed
earthaccess/results.py
earthaccess/search.py
earthaccess/services.py
earthaccess/store.py
earthaccess/system.py
earthaccess/widgets.py
earthaccess/css/iso_bootstrap4.0.0min.css
earthaccess/css/styles.css
earthaccess/utils/_search.py
earthaccess/utils/_validation.py
earthaccess-0.15.0.dist-info/METADATA
earthaccess-0.15.0.dist-info/WHEEL
earthaccess-0.15.0.dist-info/licenses/LICENSE.txt
earthaccess-0.15.0.dist-info/RECORD
