Metadata-Version: 2.4
Name: earthaccess
Version: 0.15.0
Summary: Client library for NASA Earthdata APIs
Project-URL: Repository, https://github.com/nsidc/earthaccess
Project-URL: Documentation, https://earthaccess.readthedocs.io
Project-URL: Bug Tracker, https://github.com/nsidc/earthaccess/issues
Project-URL: Changelog, https://github.com/nsidc/earthaccess/blob/main/CHANGELOG.md
Author: earthaccess contributors
Maintainer-email: Luis Lopez <betolin@gmail.com>, "Joseph H. Kennedy" <jhkennedy@alaska.edu>, James Bourbeau <james@coiled.io>, Matt Fisher <mfisher87@gmail.com>, Chuck Daniels <chuck@developmentseed.org>
License-Expression: MIT
License-File: LICENSE.txt
Classifier: Development Status :: 4 - Beta
Classifier: Environment :: Console
Classifier: Framework :: IPython
Classifier: Intended Audience :: Science/Research
Classifier: License :: OSI Approved :: MIT License
Classifier: Operating System :: MacOS
Classifier: Operating System :: Microsoft :: Windows
Classifier: Operating System :: POSIX :: Linux
Classifier: Programming Language :: Python :: 3.11
Classifier: Programming Language :: Python :: 3.12
Classifier: Programming Language :: Python :: 3.13
Classifier: Topic :: Software Development
Classifier: Topic :: Software Development :: Libraries
Requires-Python: >=3.11
Requires-Dist: fsspec>=2025.2
Requires-Dist: importlib-resources>=6.3.2
Requires-Dist: multimethod>=1.8
Requires-Dist: pqdm>=0.1
Requires-Dist: python-cmr>=0.10.0
Requires-Dist: requests>=2.26
Requires-Dist: s3fs>=2025.2
Requires-Dist: tenacity>=9.0
Requires-Dist: tinynetrc>=1.3.1
Requires-Dist: typing-extensions>=4.10.0
Provides-Extra: dev
Requires-Dist: bump-my-version>=0.10.0; extra == 'dev'
Requires-Dist: nox; extra == 'dev'
Requires-Dist: pre-commit>=2.4; extra == 'dev'
Requires-Dist: ruff>=0.6.3; extra == 'dev'
Requires-Dist: uv>=0.4.7; extra == 'dev'
Provides-Extra: docs
Requires-Dist: cartopy>=0.24.1; extra == 'docs'
Requires-Dist: cftime>=1.6.4; extra == 'docs'
Requires-Dist: dask; extra == 'docs'
Requires-Dist: dask>=2024.8.0; extra == 'docs'
Requires-Dist: fastparquet>=2023.4.0; extra == 'docs'
Requires-Dist: h5netcdf>=0.11; extra == 'docs'
Requires-Dist: h5py>=3.14.0; extra == 'docs'
Requires-Dist: ipywidgets>=7.7.0; extra == 'docs'
Requires-Dist: jupyterlab>=3; extra == 'docs'
Requires-Dist: kerchunk>=0.2.9; extra == 'docs'
Requires-Dist: lxml-html-clean>=0.1.1; extra == 'docs'
Requires-Dist: markdown-callouts>=0.2.0; extra == 'docs'
Requires-Dist: markdown-include>=0.6; extra == 'docs'
Requires-Dist: matplotlib>=3.3; extra == 'docs'
Requires-Dist: mkdocs!=1.6.0,>=1.2; extra == 'docs'
Requires-Dist: mkdocs-jupyter>=0.19.0; extra == 'docs'
Requires-Dist: mkdocs-material<10.0,>=7.1; extra == 'docs'
Requires-Dist: mkdocs-mermaid2-plugin>=1.2.1; extra == 'docs'
Requires-Dist: mkdocs-redirects>=1.2.1; extra == 'docs'
Requires-Dist: mkdocstrings[python]>=0.19.0; extra == 'docs'
Requires-Dist: numcodecs>=0.16.2; extra == 'docs'
Requires-Dist: numpy>=1.26.4; extra == 'docs'
Requires-Dist: obstore>=0.8.0; extra == 'docs'
Requires-Dist: pygments>=2.11.1; extra == 'docs'
Requires-Dist: pymdown-extensions>=9.2; extra == 'docs'
Requires-Dist: pyproj>=3.5.0; (python_version < '3.12') and extra == 'docs'
Requires-Dist: pyproj>=3.6.1; (python_version >= '3.12') and extra == 'docs'
Requires-Dist: virtualizarr>=2.1.2; extra == 'docs'
Requires-Dist: widgetsnbextension>=3.6.0; extra == 'docs'
Requires-Dist: xarray; extra == 'docs'
Requires-Dist: zarr>=3.1.1; extra == 'docs'
Provides-Extra: kerchunk
Requires-Dist: dask; extra == 'kerchunk'
Requires-Dist: h5netcdf; extra == 'kerchunk'
Requires-Dist: h5py>=3.14.0; extra == 'kerchunk'
Requires-Dist: kerchunk>=0.2.9; extra == 'kerchunk'
Requires-Dist: xarray>=2025.04.0; extra == 'kerchunk'
Requires-Dist: zarr>=3.1.1; extra == 'kerchunk'
Provides-Extra: test
Requires-Dist: dask; extra == 'test'
Requires-Dist: dask[distributed]>=2025.7.0; extra == 'test'
Requires-Dist: fastparquet>=2023.4.0; extra == 'test'
Requires-Dist: h5netcdf; extra == 'test'
Requires-Dist: h5py>=3.14.0; extra == 'test'
Requires-Dist: kerchunk>=0.2.9; extra == 'test'
Requires-Dist: mypy>=1.11.2; extra == 'test'
Requires-Dist: numcodecs>=0.16.2; extra == 'test'
Requires-Dist: numpy>=1.26.4; extra == 'test'
Requires-Dist: obstore>=0.8.0; extra == 'test'
Requires-Dist: pytest-cov>=5.0; extra == 'test'
Requires-Dist: pytest-watch>=4.2; extra == 'test'
Requires-Dist: pytest>=8.3; extra == 'test'
Requires-Dist: python-magic>=0.4; extra == 'test'
Requires-Dist: responses>=0.14; extra == 'test'
Requires-Dist: types-requests>=0.1; extra == 'test'
Requires-Dist: types-setuptools>=0.1; extra == 'test'
Requires-Dist: vcrpy>=7.0.0; extra == 'test'
Requires-Dist: virtualizarr>=2.1.2; extra == 'test'
Requires-Dist: xarray; extra == 'test'
Requires-Dist: xarray>=2025.04.0; extra == 'test'
Requires-Dist: zarr>=3.1.1; extra == 'test'
Provides-Extra: virtualizarr
Requires-Dist: dask; extra == 'virtualizarr'
Requires-Dist: fastparquet>=2023.4.0; extra == 'virtualizarr'
Requires-Dist: h5py>=3.14.0; extra == 'virtualizarr'
Requires-Dist: kerchunk>=0.2.9; extra == 'virtualizarr'
Requires-Dist: numcodecs>=0.16.2; extra == 'virtualizarr'
Requires-Dist: numpy>=1.26.4; extra == 'virtualizarr'
Requires-Dist: obstore>=0.8.0; extra == 'virtualizarr'
Requires-Dist: virtualizarr>=2.1.2; extra == 'virtualizarr'
Requires-Dist: xarray; extra == 'virtualizarr'
Requires-Dist: zarr>=3.1.1; extra == 'virtualizarr'
